invogen/__init__.py
invogen/accounts.py
invogen/invoice.py
invogen/template.py
invogen/templates/default.tex
test/__init__.py
test/conftest.py
test/test_accounts.py
test/test_invoice.py
invogen-0.3.0.dist-info/LICENSE
invogen-0.3.0.dist-info/METADATA
invogen-0.3.0.dist-info/WHEEL
invogen-0.3.0.dist-info/top_level.txt
invogen-0.3.0.dist-info/RECORD
