Metadata-Version: 2.1
Name: invogen
Version: 0.3.0
Summary: Generate beautiful invoices using Python.
Home-page: https://github.com/samueljsb/InvoGen
Author: Samuel Searles-Bryant
Author-email: devel@samueljsb.co.uk
License: MIT
Project-URL: Documentation, https://invogen.readthedocs.io
Project-URL: Bug Reports, https://github.com/samueljsb/InvoGen/issues
Platform: UNKNOWN
Classifier: Development Status :: 3 - Alpha
Classifier: License :: OSI Approved :: MIT License
Classifier: Programming Language :: Python :: 3.5
Classifier: Programming Language :: Python :: 3.6
Classifier: Programming Language :: Python :: 3.7
Requires-Dist: Jinja2 (>=2.10)
